{
    "panel" : {
        "adminPanel" : "admin"
    },
    "header" : {
        "title" : "Dance your live",
        "subtitle01" : "Dance with passionate people",
        "subtitle02" : "-Join us below-",
        "button" : "Join us!"
    },
    "navigation" : {
        "home" : {
            "label" : "home",
            "link" : "/"
        },
        "about" : {
            "label" : "about",
            "link" : "/about"
        },
        "gallery" : {
            "label" : "gallery",
            "link" : "/gallery"
        },
        "contact" : {
            "label" : "contact",
            "link" : "/contact"
        },
        "store" : {
            "label" : "store",
            "link" : "/store"
        }
    },
    "footer" : {
        "sign" : "ARWcode 2023 Powered by React Vite",
        "link" : "Videos by mixkit.co"
    }
}